ipyform/__init__.py
ipyform/entities.py
ipyform/env.py
ipyform/ipython_ext.py
ipyform/parser.py
ipyform/py.typed
ipyform/widgets.py
ipyform-0.1.1.dist-info/METADATA
ipyform-0.1.1.dist-info/WHEEL
ipyform-0.1.1.dist-info/licenses/LICENSE
ipyform-0.1.1.dist-info/RECORD
