Metadata-Version: 2.3
Name: ipyform
Version: 0.1.1
Summary: Extension to render Google Colab Form on regular Jupyter Notebooks
Project-URL: Homepage, https://phihung.github.io/ipyform/
Project-URL: Source, https://github.com/phihung/ipyform
License-File: LICENSE
Requires-Python: >=3.9
Requires-Dist: chompjs
Requires-Dist: ipywidgets
Requires-Dist: markdown
